pagelove/__init__.py
pagelove-0.1.0.dist-info/licenses/LICENSE
pagelove-0.1.0.dist-info/METADATA
pagelove-0.1.0.dist-info/WHEEL
pagelove-0.1.0.dist-info/top_level.txt
pagelove-0.1.0.dist-info/RECORD
