Metadata-Version: 2.4
Name: pagelove
Version: 0.1.0
Summary: Pagelove - Delivering the promise of the web
Author-email: Sam Johnston <sam@pagelove.team>
License: MIT
Project-URL: Homepage, https://pagelove.org
Project-URL: Repository, https://github.com/pagelove/pagelove-py
Keywords: pagelove,web
Classifier: Development Status :: 3 - Alpha
Classifier: Intended Audience :: Developers
Classifier: License :: OSI Approved :: MIT License
Classifier: Programming Language :: Python :: 3
Classifier: Programming Language :: Python :: 3.8
Classifier: Programming Language :: Python :: 3.9
Classifier: Programming Language :: Python :: 3.10
Classifier: Programming Language :: Python :: 3.11
Classifier: Programming Language :: Python :: 3.12
Requires-Python: >=3.8
License-File: LICENSE
Dynamic: license-file
